topsis/__init__.py
topsis/topsis.py
topsis_dishavpreet_102353006-0.0.2.dist-info/licenses/LICENSE
topsis_dishavpreet_102353006-0.0.2.dist-info/METADATA
topsis_dishavpreet_102353006-0.0.2.dist-info/WHEEL
topsis_dishavpreet_102353006-0.0.2.dist-info/entry_points.txt
topsis_dishavpreet_102353006-0.0.2.dist-info/top_level.txt
topsis_dishavpreet_102353006-0.0.2.dist-info/RECORD
