Metadata-Version: 2.4
Name: Topsis-Dishavpreet-102353006
Version: 0.0.2
Summary: Implementation of TOPSIS method
Author: Dishavpreet
Author-email: dishav1202@gmail.com
License-File: LICENSE
Requires-Dist: numpy
Requires-Dist: pandas
Dynamic: author
Dynamic: author-email
Dynamic: description
Dynamic: description-content-type
Dynamic: license-file
Dynamic: requires-dist
Dynamic: summary
